guest_user/__init__.py
guest_user/admin.py
guest_user/app_settings.py
guest_user/apps.py
guest_user/backends.py
guest_user/checks.py
guest_user/contrib/allauth/__init__.py
guest_user/contrib/allauth/apps.py
guest_user/contrib/allauth/signals.py
guest_user/decorators.py
guest_user/exceptions.py
guest_user/forms.py
guest_user/functions.py
guest_user/management/__init__.py
guest_user/management/commands/__init__.py
guest_user/management/commands/delete_expired_users.py
guest_user/migrations/0001_initial.py
guest_user/migrations/__init__.py
guest_user/mixins.py
guest_user/models.py
guest_user/settings.py
guest_user/signals.py
guest_user/templates/guest_user/convert_form.html
guest_user/templates/guest_user/convert_success.html
guest_user/templatetags/__init__.py
guest_user/templatetags/guest_user.py
guest_user/urls.py
guest_user/views.py
django_guest_user-0.5.2.dist-info/LICENSE
django_guest_user-0.5.2.dist-info/WHEEL
django_guest_user-0.5.2.dist-info/METADATA
django_guest_user-0.5.2.dist-info/RECORD
