Metadata-Version: 2.1
Name: django-guest-user
Version: 0.5.2
Summary: A Django app that lets visitors interact with your site without registration.
Home-page: https://github.com/julianwachholz/django-guest-user
License: MIT
Author: Julian Wachholz
Author-email: julian@wachholz.ch
Requires-Python: >=3.7,<4.0
Classifier: Development Status :: 4 - Beta
Classifier: Framework :: Django
Classifier: Framework :: Django :: 3.2
Classifier: Framework :: Django :: 4.0
Classifier: License :: OSI Approved :: MIT License
Classifier: Programming Language :: Python :: 3
Classifier: Programming Language :: Python :: 3.10
Classifier: Programming Language :: Python :: 3.7
Classifier: Programming Language :: Python :: 3.8
Classifier: Programming Language :: Python :: 3.9
Classifier: Topic :: Software Development :: Libraries :: Python Modules
Project-URL: Repository, https://github.com/julianwachholz/django-guest-user
